LICENSE.md
README.md
setup.cfg
setup.py
platform_analysis/__init__.py
platform_analysis/discourse.py
platform_analysis/git.py
platform_analysis/github_analysis.py
platform_analysis/hg.py
platform_analysis/mailman.py
platform_analysis/sna.py
platform_analysis/svn.py
platform_analysis/twitter_sna.py
platform_analysis/utils.py
platform_analysis.egg-info/PKG-INFO
platform_analysis.egg-info/SOURCES.txt
platform_analysis.egg-info/dependency_links.txt
platform_analysis.egg-info/requires.txt
platform_analysis.egg-info/top_level.txt