Metadata-Version: 2.1
Name: platform-analysis
Version: 0.31
Summary: A Python library for Social Network Analysis of online collaboration platforms and tools like Twitter, YouTube and Git, Hg, SVN, GitHub, GitLab, BitBucket repositories
Home-page: https://github.com/openp2pdesign/platform_analysis
Download-URL: https://github.com/openp2pdesign/platform_analysis/releases/tag/v0.31
Author: Massimo Menichinelli
Author-email: info@openp2pdesign.org
License: UNKNOWN
Keywords: Git,Hg,Mercurial,SVN,Subversion,GitHub,BitBucket,Twitter,Social Network Analysis,SNA
Platform: UNKNOWN
Classifier: Development Status :: 3 - Alpha
Classifier: Topic :: Utilities
Classifier: Environment :: Web Environment
Classifier: Operating System :: OS Independent
Classifier: Intended Audience :: Science/Research
Classifier: Programming Language :: Python
Classifier: Programming Language :: Python :: 3
Classifier: License :: OSI Approved :: GNU Lesser General Public License v3 (LGPLv3)
License-File: LICENSE.md
